{
  "RUN_FIELDS": [
    "run_id", "date", "title", "experimenter",
    "result_summary", "raw_path", "notes"
  ],
  "STEP_FIELDS": ["run_id", "step_no", "action"],
  "SERIES_FIELDS": ["series_id"],
  "COLS": [
    ["run_id", 110], ["date", 100], ["title", 180],
    ["result_summary", 300]
  ],
  "HEAD": {
    "run_id": "Run ID", "date": "Date", "title": "Title",
    "result_summary": "Result"
  },
  "LONG_FIELDS": ["result_summary", "notes"],
  "HIDDEN_EDIT_FIELDS": [],
  "JP_LABEL": {
    "run_id": "記録ID", "date": "日付", "title": "タイトル",
    "experimenter": "担当者", "result_summary": "結果概要",
    "raw_path": "元データCSV", "notes": "メモ"
  },
  "CHOICES": {},
  "GCOL": {},
  "STEP_FORM": [["action", "Action"]],
  "ACTION_CHOICES": [],
  "MEDIA_SEEDS": [],
  "features": {
    "steps": false,
    "series": false,
    "grading": false,
    "baseline": false
  },
  "waveform": {
    "default_mode": "all",
    "step_markers": false,
    "modes": [
      {
        "id": "all",
        "label": "Channels",
        "y_label": "Value",
        "channels": "all"
      }
    ]
  },
  "facets": [],
  "adv_filters": ["date_range", "experimenter"],
  "LABEL_EN": {
    "run_id": "Run ID", "date": "Date", "title": "Title",
    "experimenter": "Researcher", "result_summary": "Result Summary",
    "raw_path": "Source CSV", "notes": "Notes"
  }
}
